README.md
setup.py
pegasus/__init__.py
pegasus/dados/__init__.py
pegasus/dados/load_all.py
pegasus/dados/load_any.py
pegasus/dados/files/__init__.py
pegasus/dados/files/CNES/CBO_OUT_4_DBF_ANOS_2006_2019.xlsx
pegasus/dados/files/CNES/CNES_OUT_CADGER_XX_ANOS_2008_2019.xlsx
pegasus/dados/files/CNES/IDEQUIPE_OUT_27_EQP_XX_ANOS_2008_2019.xlsx
pegasus/dados/files/CNES/ID_AREA_OUT_27_AREA_XX_ANOS_2008_2019.xlsx
pegasus/dados/files/CNES/ID_SEGM_OUT_27_SEGM_XX_ANOS_2008_2019.xlsx
pegasus/dados/files/CNES/RSAUDE.xlsx
pegasus/dados/files/CNES/__init__.py
pegasus/dados/files/SIA/CBO_OUT_4_DBF_ANOS_2006_2019.xlsx
pegasus/dados/files/SIA/COD_PROCEDIMENTOS_OUT_TB_SIGTAP_ANOS_2008_2019.xlsx
pegasus/dados/files/SIA/PA_CODUNI_OUT_CADGER_XX_ANOS_2008_2019.xlsx
pegasus/dados/files/SIA/RSAUDE.xlsx
pegasus/dados/files/SIA/__init__.py
pegasus/dados/files/SIH/CNES_OUT_TCNESBR_PLUS_ANOS_2008_2019.xlsx
pegasus/dados/files/SIH/COD_PROCEDIMENTOS_OUT_TB_SIGTAP_ANOS_2008_2019.xlsx
pegasus/dados/files/SIH/RSAUDE.xlsx
pegasus/dados/files/SIH/SERV_CLA_OUT_S_CLASSEN_ANOS_2008_2019.xlsx
pegasus/dados/files/SIH/__init__.py
pegasus/dados/files/SIM/CAUSABAS_OUT_CID10_ANOS_1997_2017.xlsx
pegasus/dados/files/SIM/CODESTAB_OUT_CNESDO18_E_3TCC_ANOS_1997_2017.xlsx
pegasus/dados/files/SIM/NATURAL_OUT_NAT1212_ANOS_1997_2017.xlsx
pegasus/dados/files/SIM/OCUP_OUT_TABOCUP_E_2TCC_ANOS_1997_2017.xlsx
pegasus/dados/files/SIM/RSAUDE.xlsx
pegasus/dados/files/SIM/TPMORTEOCO.xlsx
pegasus/dados/files/SIM/TPOBITOCOR.xlsx
pegasus/dados/files/SIM/__init__.py
pegasus/dados/files/SINAN/RSAUDE.xlsx
pegasus/dados/files/SINAN/__init__.py
pegasus/dados/files/SINASC/CODESTAB_OUT_CNESDN_07_E_18_ANOS_1997_2017.xlsx
pegasus/dados/files/SINASC/CODOCUPMAE_OUT_TABOCUP_E_2TCC_ANOS_1997_2017.xlsx
pegasus/dados/files/SINASC/RSAUDE.xlsx
pegasus/dados/files/SINASC/STTRABPART.xlsx
pegasus/dados/files/SINASC/TPAPRESENT.xlsx
pegasus/dados/files/SINASC/TPFUNCRESP.xlsx
pegasus/dados/files/SINASC/__init__.py
pegasus/dados/insertion/__init__.py
pegasus_dados.egg-info/PKG-INFO
pegasus_dados.egg-info/SOURCES.txt
pegasus_dados.egg-info/dependency_links.txt
pegasus_dados.egg-info/requires.txt
pegasus_dados.egg-info/top_level.txt