Metadata-Version: 2.1
Name: pegasus-dados
Version: 0.2.0
Summary: Plataforma Eletrônica de Governança e Accountability do SUS - Módulo dados
Home-page: https://github.com/SecexSaudeTCU/pegasus/tree/master/pegasus/dados
Author: SecexSaudeTCU
Author-email: ericlb@tcu.gov.br
License: UNKNOWN
Platform: UNKNOWN
Classifier: Programming Language :: Python :: 3
Classifier: License :: OSI Approved :: MIT License
Requires-Python: >=3.6
